{
  "db_name": "PostgreSQL",
  "query": "select id, username, email from users where id = $1",
  "describe": {
    "columns": [
      {
        "ordinal": 0,
        "name": "id",
        "type_info": "Int4"
      },
      {
        "ordinal": 1,
        "name": "username",
        "type_info": "Text"
      },
      {
        "ordinal": 2,
        "name": "email",
        "type_info": {
          "Custom": {
            "name": "citext",
            "kind": "Simple"
          }
        }
      }
    ],
    "parameters": {
      "Left": [
        "Int4"
      ]
    },
    "nullable": [
      false,
      false,
      false
    ]
  },
  "hash": "1d32623ef89fa28eeeab55864f2e7e8b524e4feb9848320e25176d2ea6f45b01"
}
